ollamax/__init__.py
ollamax/ollamax.py
ollamax-5.0.0.dist-info/METADATA
ollamax-5.0.0.dist-info/WHEEL
ollamax-5.0.0.dist-info/top_level.txt
ollamax-5.0.0.dist-info/RECORD
